mc_monitor_helper_package/__init__.py
mc_monitor_helper_package/api_functions.py
mc_monitor_helper_package/auth.py
mc_monitor_helper_package/client.py
mc_monitor_helper_package/exceptions.py
mc_monitor_helper_package/mc_state.py
mc_monitor_helper_package/mc_table.py
mc_monitor_helper_package/mc_update.py
mc_monitor_helper_package/queries.py
mc_monitor_helper_package-0.1.1.dist-info/LICENSE
mc_monitor_helper_package-0.1.1.dist-info/WHEEL
mc_monitor_helper_package-0.1.1.dist-info/METADATA
mc_monitor_helper_package-0.1.1.dist-info/RECORD
