Metadata-Version: 2.1
Name: mc-monitor-helper-package
Version: 0.1.1
Summary: Utility package for setting and updating monte carlo monitors
Home-page: https://github.com/Gitznik/monte_carlo_helper_package
License: GPL-3.0-or-later
Keywords: monte carlo,quality,monitoring,data governance
Author: Gitznik
Author-email: r.offner@gmx.de
Requires-Python: >=3.7,<4.0
Classifier: Development Status :: 3 - Alpha
Classifier: Intended Audience :: Developers
Classifier: License :: OSI Approved :: GNU General Public License v3 or later (GPLv3+)
Classifier: Programming Language :: Python :: 3
Classifier: Programming Language :: Python :: 3.10
Classifier: Programming Language :: Python :: 3.7
Classifier: Programming Language :: Python :: 3.8
Classifier: Programming Language :: Python :: 3.9
Classifier: Topic :: Utilities
Requires-Dist: gql (>=2.0.0,<3.0.0)
Project-URL: Repository, https://github.com/Gitznik/monte_carlo_helper_package
